propulsionai/__init__.py
propulsionai/_base_client.py
propulsionai/_client.py
propulsionai/_compat.py
propulsionai/_constants.py
propulsionai/_exceptions.py
propulsionai/_files.py
propulsionai/_models.py
propulsionai/_qs.py
propulsionai/_resource.py
propulsionai/_response.py
propulsionai/_streaming.py
propulsionai/_types.py
propulsionai/_version.py
propulsionai/py.typed
propulsionai/_utils/__init__.py
propulsionai/_utils/_logs.py
propulsionai/_utils/_proxy.py
propulsionai/_utils/_reflection.py
propulsionai/_utils/_streams.py
propulsionai/_utils/_sync.py
propulsionai/_utils/_transform.py
propulsionai/_utils/_typing.py
propulsionai/_utils/_utils.py
propulsionai/lib/.keep
propulsionai/lib/tool_helper.py
propulsionai/lib/tool_runner.py
propulsionai/lib/tool_runner_async.py
propulsionai/resources/__init__.py
propulsionai/resources/chat/__init__.py
propulsionai/resources/chat/chat.py
propulsionai/resources/chat/completions.py
propulsionai/resources/dataset/__init__.py
propulsionai/resources/dataset/dataset.py
propulsionai/resources/dataset/item.py
propulsionai/resources/knowledgebase/__init__.py
propulsionai/resources/knowledgebase/file.py
propulsionai/resources/knowledgebase/item.py
propulsionai/resources/knowledgebase/knowledgebase.py
propulsionai/types/__init__.py
propulsionai/types/dataset_create_params.py
propulsionai/types/dataset_create_response.py
propulsionai/types/knowledgebase_create_params.py
propulsionai/types/chat/__init__.py
propulsionai/types/chat/completion_create_chunk.py
propulsionai/types/chat/completion_create_params.py
propulsionai/types/chat/completion_create_response.py
propulsionai/types/dataset/__init__.py
propulsionai/types/dataset/item_create_params.py
propulsionai/types/dataset/item_create_response.py
propulsionai/types/knowledgebase/__init__.py
propulsionai/types/knowledgebase/file.py
propulsionai/types/knowledgebase/file_create_params.py
propulsionai/types/knowledgebase/file_delete_response.py
propulsionai-0.16.1.dist-info/METADATA
propulsionai-0.16.1.dist-info/WHEEL
propulsionai-0.16.1.dist-info/licenses/LICENSE
propulsionai-0.16.1.dist-info/RECORD
